flwr_custom/__init__.py
flwr_custom/client/__init__.py
flwr_custom/client/app.py
flwr_custom/client/client.py
flwr_custom/client/dpfedavg_numpy_client.py
flwr_custom/client/numpy_client.py
flwr_custom/client/grpc_client/__init__.py
flwr_custom/client/grpc_client/connection.py
flwr_custom/client/message_handler/__init__.py
flwr_custom/client/message_handler/message_handler.py
flwr_custom/client/message_handler/task_handler.py
flwr_custom/client/rest_client/__init__.py
flwr_custom/client/rest_client/connection.py
flwr_custom/common/__init__.py
flwr_custom/common/address.py
flwr_custom/common/constant.py
flwr_custom/common/date.py
flwr_custom/common/dp.py
flwr_custom/common/grpc.py
flwr_custom/common/logger.py
flwr_custom/common/parameter.py
flwr_custom/common/serde.py
flwr_custom/common/telemetry.py
flwr_custom/common/typing.py
flwr_custom/common/version.py
flwr_custom/driver/__init__.py
flwr_custom/driver/driver.py
flwr_custom/proto/__init__.py
flwr_custom/proto/driver_pb2.py
flwr_custom/proto/driver_pb2_grpc.py
flwr_custom/proto/fleet_pb2.py
flwr_custom/proto/fleet_pb2_grpc.py
flwr_custom/proto/node_pb2.py
flwr_custom/proto/node_pb2_grpc.py
flwr_custom/proto/task_pb2.py
flwr_custom/proto/task_pb2_grpc.py
flwr_custom/proto/transport_pb2.py
flwr_custom/proto/transport_pb2_grpc.py
flwr_custom/server/__init__.py
flwr_custom/server/app.py
flwr_custom/server/client_manager.py
flwr_custom/server/client_proxy.py
flwr_custom/server/criterion.py
flwr_custom/server/history.py
flwr_custom/server/server.py
flwr_custom/server/driver/__init__.py
flwr_custom/server/driver/driver_servicer.py
flwr_custom/server/fleet/__init__.py
flwr_custom/server/fleet/fleet_servicer.py
flwr_custom/server/grpc_server/__init__.py
flwr_custom/server/grpc_server/driver_client_manager.py
flwr_custom/server/grpc_server/flower_service_servicer.py
flwr_custom/server/grpc_server/grpc_bridge.py
flwr_custom/server/grpc_server/grpc_client_proxy.py
flwr_custom/server/grpc_server/grpc_server.py
flwr_custom-0.1.2.dist-info/METADATA
flwr_custom-0.1.2.dist-info/WHEEL
flwr_custom-0.1.2.dist-info/top_level.txt
flwr_custom-0.1.2.dist-info/RECORD
